fastapi_apollo_middleware/__init__.py
fastapi_apollo_middleware/_version.py
fastapi_apollo_middleware/middleware/__init__.py
fastapi_apollo_middleware/middleware/decorator.py
fastapi_apollo_middleware/middleware/exceptions.py
fastapi_apollo_middleware-0.1.0.dist-info/LICENSE
fastapi_apollo_middleware-0.1.0.dist-info/METADATA
fastapi_apollo_middleware-0.1.0.dist-info/WHEEL
fastapi_apollo_middleware-0.1.0.dist-info/top_level.txt
fastapi_apollo_middleware-0.1.0.dist-info/RECORD
